boaboard-0.1.0.dist-info/METADATA
boaboard-0.1.0.dist-info/WHEEL
boaboard-0.1.0.dist-info/entry_points.txt
boaboard-0.1.0.dist-info/licenses/LICENSE
boaboard/__init__.py
boaboard/__main__.py
boaboard-0.1.0.dist-info/RECORD
